{
    "hunting": [
        {
            "id": 1,
            "title": "세종시, 7~9일 원수산·전월산 유해야생동물 일제포획",
            "excerpt": "지난해 세종에서는 멧돼지 205마리와 고라니 954마리 등 모두 1159마리의 유해야생동물을 포획했다. 손영민 동물정책과장은 \"이번 일제 포획은...",
            "body": "네이버 뉴스 검색 결과입니다.<br><br>지난해 세종에서는 멧돼지 205마리와 고라니 954마리 등 모두 1159마리의 유해야생동물을 포획했다. 손영민 동물정책과장은 \"이번 일제 포획은 시민 안전과 파종기 농작물 피해 예방을 위한 불가피한 조치\"라며 \"포획을... <br><br><a href='https://n.news.naver.com/mnews/article/421/0008802146?sid=102' target='_blank' style='color:#3a86ff; text-decoration:underline;'>원문 기사 보러가기</a>",
            "source": "네이버 뉴스",
            "image": "images/boar.png",
            "daysAgo": 0,
            "date": "26.03.03",
            "link": "https://n.news.naver.com/mnews/article/421/0008802146?sid=102"
        },
        {
            "id": 2,
            "title": "'멧돼지 일제포획'·'학교급식 합동점검' 동시 추진…봄철 안전관리 강...",
            "excerpt": "세종특별자치시가 도심 멧돼지 출몰 증가에 따른 안전사고 예방과 봄철 식중독 방지를 위해 유해야생동물 일제포획과 학교급식 합동점검을 잇달아 실시한...",
            "body": "네이버 뉴스 검색 결과입니다.<br><br>세종특별자치시가 도심 멧돼지 출몰 증가에 따른 안전사고 예방과 봄철 식중독 방지를 위해 유해야생동물 일제포획과 학교급식 합동점검을 잇달아 실시한다. ◇ 원수산·전월산 멧돼지 집중 포획 시는 오는 7일부터... <br><br><a href='https://www.bzeronews.com/news/articleView.html?idxno=812646' target='_blank' style='color:#3a86ff; text-decoration:underline;'>원문 기사 보러가기</a>",
            "source": "네이버 뉴스",
            "image": "images/boar.png",
            "daysAgo": 0,
            "date": "26.03.03",
            "link": "https://www.bzeronews.com/news/articleView.html?idxno=812646"
        },
        {
            "id": 3,
            "title": "야생 멧돼지·너구리 어디서 많이 출몰하나…지도로 본다",
            "excerpt": "기후에너지환경부 소속 국립생물자원관은 2023년부터 무인기·무인 카메라와 포획·조사 등을 통해 도심... 너구리 주요 출몰 지역은 그간 야생동물...",
            "body": "네이버 뉴스 검색 결과입니다.<br><br>기후에너지환경부 소속 국립생물자원관은 2023년부터 무인기·무인 카메라와 포획·조사 등을 통해 도심... 너구리 주요 출몰 지역은 그간 야생동물 관련 민원이 빈번했던 지역들이 다수 포함돼 있다. 해당 지역들은... <br><br><a href='https://n.news.naver.com/mnews/article/003/0013788793?sid=101' target='_blank' style='color:#3a86ff; text-decoration:underline;'>원문 기사 보러가기</a>",
            "source": "네이버 뉴스",
            "image": "images/boar.png",
            "daysAgo": 5,
            "date": "26.02.26",
            "link": "https://n.news.naver.com/mnews/article/003/0013788793?sid=101"
        },
        {
            "id": 4,
            "title": "영산강청, 장성 일대서 야생동물 불법 엽구 27점 수거",
            "excerpt": "영산강청에 따르면 장성군과 내장산 국립공원 백암사무소, 야생생물관리협회 광주전남지부 등 유관기관이 함께한 이번 수거는 겨울철 먹이 부족으로 민가...",
            "body": "네이버 뉴스 검색 결과입니다.<br><br>영산강청에 따르면 장성군과 내장산 국립공원 백암사무소, 야생생물관리협회 광주전남지부 등 유관기관이 함께한 이번 수거는 겨울철 먹이 부족으로 민가 인근까지 내려오는 야생동물을 노린 불법 포획 행위를 근절하기... <br><br><a href='https://n.news.naver.com/mnews/article/421/0008793478?sid=102' target='_blank' style='color:#3a86ff; text-decoration:underline;'>원문 기사 보러가기</a>",
            "source": "네이버 뉴스",
            "image": "images/hunter.png",
            "daysAgo": 6,
            "date": "26.02.25",
            "link": "https://n.news.naver.com/mnews/article/421/0008793478?sid=102"
        },
        {
            "id": 5,
            "title": "춘천시, 유해야생동물 피해방지단 운영",
            "excerpt": "포획 허가 야생동물은 멧돼지, 고라니, 까치, 까마귀, 멧비둘기, 민물가마우지 등이다. 멧돼지 포획 실적은 2023년 693마리에서 2024년 ...",
            "body": "네이버 뉴스 검색 결과입니다.<br><br>포획 허가 야생동물은 멧돼지, 고라니, 까치, 까마귀, 멧비둘기, 민물가마우지 등이다. 멧돼지 포획 실적은 2023년 693마리에서 2024년 1,364마리, 지난해 1,522마리로 늘고 있다.<br><br><a href='https://n.news.naver.com/mnews/article/087/0001176828?sid=102' target='_blank' style='color:#3a86ff; text-decoration:underline;'>원문 기사 보러가기</a>",
            "source": "네이버 뉴스",
            "image": "images/boar.png",
            "daysAgo": 4,
            "date": "26.02.27",
            "link": "https://n.news.naver.com/mnews/article/087/0001176828?sid=102"
        },
        {
            "id": 6,
            "title": "춘천시, 2026년 유해야생동물 피해방지단 운영",
            "excerpt": "춘천시에 농ㆍ어가의 생업에 야생생물로 인한 피해신고가 접수되면 시는 포획범위와 기간을 정해 유해야생동물을 포획 허가하게 되며 피해방지단은 해당 ...",
            "body": "네이버 뉴스 검색 결과입니다.<br><br>춘천시에 농ㆍ어가의 생업에 야생생물로 인한 피해신고가 접수되면 시는 포획범위와 기간을 정해 유해야생동물을 포획 허가하게 되며 피해방지단은 해당 유해야생동물의 포획을 담당하게 된다. ▼사진=춘천시... <br><br><a href='https://www.gukjenews.com/news/articleView.html?idxno=3516642' target='_blank' style='color:#3a86ff; text-decoration:underline;'>원문 기사 보러가기</a>",
            "source": "네이버 뉴스",
            "image": "images/hunter.png",
            "daysAgo": 3,
            "date": "26.02.28",
            "link": "https://www.gukjenews.com/news/articleView.html?idxno=3516642"
        },
        {
            "id": 7,
            "title": "동해시, 야생동물 피해 농가 최대 500만원 보상",
            "excerpt": "박화경 시 환경과장은 “야생동물로 인한 농작물 피해가 반복되지 않도록 포획 활동과 예방시설 지원을 지속적으로 강화하겠다”며 “피해 발생 시에는 ...",
            "body": "네이버 뉴스 검색 결과입니다.<br><br>박화경 시 환경과장은 “야생동물로 인한 농작물 피해가 반복되지 않도록 포획 활동과 예방시설 지원을 지속적으로 강화하겠다”며 “피해 발생 시에는 신속하고 공정한 보상을 통해 농가의 어려움을 최소화하겠다”... <br><br><a href='https://n.news.naver.com/mnews/article/087/0001176217?sid=102' target='_blank' style='color:#3a86ff; text-decoration:underline;'>원문 기사 보러가기</a>",
            "source": "네이버 뉴스",
            "image": "images/hunter.png",
            "daysAgo": 6,
            "date": "26.02.25",
            "link": "https://n.news.naver.com/mnews/article/087/0001176217?sid=102"
        },
        {
            "id": 8,
            "title": "동해시, 야생동물 농작물 피해보상 지원",
            "excerpt": "박화경 환경과장은 \"야생동물 피해가 반복되지 않도록 포획 활동과 예방시설 지원을 확대하고, 피해 발생 시 신속하고 공정한 보상으로 농가의 어려움...",
            "body": "네이버 뉴스 검색 결과입니다.<br><br>박화경 환경과장은 \"야생동물 피해가 반복되지 않도록 포획 활동과 예방시설 지원을 확대하고, 피해 발생 시 신속하고 공정한 보상으로 농가의 어려움을 최소화하겠다\"고 밝혔다.<br><br><a href='https://www.gukjenews.com/news/articleView.html?idxno=3515349' target='_blank' style='color:#3a86ff; text-decoration:underline;'>원문 기사 보러가기</a>",
            "source": "네이버 뉴스",
            "image": "images/hunter.png",
            "daysAgo": 5,
            "date": "26.02.26",
            "link": "https://www.gukjenews.com/news/articleView.html?idxno=3515349"
        },
        {
            "id": 9,
            "title": "국립공원 곳곳에 숨겨놨다…\"밟으면 절단, 사람도 위험\"",
            "excerpt": "대부분 야생동물 불법 포획용입니다. [이효경/지리산국립공원경남사무소 자원보전과장 : 요즘은 이제 약용을 목적으로 오소리나 산양 포획이 이루어지고...",
            "body": "네이버 뉴스 검색 결과입니다.<br><br>대부분 야생동물 불법 포획용입니다. [이효경/지리산국립공원경남사무소 자원보전과장 : 요즘은 이제 약용을 목적으로 오소리나 산양 포획이 이루어지고 있고, 동물 사체 방치로 인한 수질 토양 오염... <br><br><a href='https://n.news.naver.com/mnews/article/055/0001336933?sid=102' target='_blank' style='color:#3a86ff; text-decoration:underline;'>원문 기사 보러가기</a>",
            "source": "네이버 뉴스",
            "image": "images/hunter.png",
            "daysAgo": 1,
            "date": "26.03.02",
            "link": "https://n.news.naver.com/mnews/article/055/0001336933?sid=102"
        },
        {
            "id": 10,
            "title": "공격하는 들개, 때리면 처벌?",
            "excerpt": "유해야생동물로 지정되면, 포획 틀이나 마취총을 사용할 수 있음. 일부 지자체에서 야생동물 지정 소관 부처인 환경부에 유해야생동물 지정을 건의했지...",
            "body": "네이버 뉴스 검색 결과입니다.<br><br>유해야생동물로 지정되면, 포획 틀이나 마취총을 사용할 수 있음. 일부 지자체에서 야생동물 지정 소관 부처인 환경부에 유해야생동물 지정을 건의했지만, 받아들여지지 않음. - 주인이 있는 개로 인한 사고는 민법상... <br><br><a href='https://www.danbinews.com/news/articleView.html?idxno=32496' target='_blank' style='color:#3a86ff; text-decoration:underline;'>원문 기사 보러가기</a>",
            "source": "네이버 뉴스",
            "image": "images/env_gov.png",
            "daysAgo": 2,
            "date": "26.03.01",
            "link": "https://www.danbinews.com/news/articleView.html?idxno=32496"
        }
    ],
    "asf": [
        {
            "id": 11,
            "title": "합천 ASF 농장 돼지 살처분 완료…추가 확산 저지 총력전",
            "excerpt": "아프리카돼지열병(ASF)이 경남 창녕·의령에 이어 합천군까지 확산해 방역 당국에 비상이 걸렸다.... 국내 발생 초기에는 접경지 야생 멧돼지가 ...",
            "body": "네이버 뉴스 검색 결과입니다.<br><br>아프리카돼지열병(ASF)이 경남 창녕·의령에 이어 합천군까지 확산해 방역 당국에 비상이 걸렸다.... 국내 발생 초기에는 접경지 야생 멧돼지가 확산의 주요 원인이 되면서 경기 북부와 강원 북부 지역에 집중되는 모습을... <br><br><a href='https://n.news.naver.com/mnews/article/082/0001368776?sid=102' target='_blank' style='color:#3a86ff; text-decoration:underline;'>원문 기사 보러가기</a>",
            "source": "네이버 뉴스",
            "image": "images/boar.png",
            "daysAgo": 2,
            "date": "26.03.01",
            "link": "https://n.news.naver.com/mnews/article/082/0001368776?sid=102"
        },
        {
            "id": 12,
            "title": "경남 합천 돼지농장에서 아프리카돼지열병 확인",
            "excerpt": "아프리카돼지열병은 한 번 발생하면 돼지와 멧돼지에 치명적인 영향을 미친다. 고열, 식욕 부진, 기립 불능, 구토, 출혈, 폐사 등의 증상이 나타...",
            "body": "네이버 뉴스 검색 결과입니다.<br><br>아프리카돼지열병은 한 번 발생하면 돼지와 멧돼지에 치명적인 영향을 미친다. 고열, 식욕 부진, 기립 불능, 구토, 출혈, 폐사 등의 증상이 나타나며 암퇘지는 유산 확률이 높아진다. 그러나 사람에게는 감염되지 않는다.... <br><br><a href='https://n.news.naver.com/mnews/article/658/0000136422?sid=101' target='_blank' style='color:#3a86ff; text-decoration:underline;'>원문 기사 보러가기</a>",
            "source": "네이버 뉴스",
            "image": "images/boar.png",
            "daysAgo": 4,
            "date": "26.02.27",
            "link": "https://n.news.naver.com/mnews/article/658/0000136422?sid=101"
        },
        {
            "id": 13,
            "title": "전남 아프리카돼지열병 잇따라…사료 원료서 유전자 검출",
            "excerpt": "가운데 아프리카돼지열병 유전자가 검출됐다고 밝혔습니다. 그동안 야생 멧돼지나 외국인 노동자 등 해외 요인에 따라 감염됐던 것과 달리 사료 원료가...",
            "body": "네이버 뉴스 검색 결과입니다.<br><br>가운데 아프리카돼지열병 유전자가 검출됐다고 밝혔습니다. 그동안 야생 멧돼지나 외국인 노동자 등 해외 요인에 따라 감염됐던 것과 달리 사료 원료가 원인으로 추정되는 겁니다. [오재곤/한돈협회 전남도협의회장... <br><br><a href='https://n.news.naver.com/mnews/article/056/0012129905?sid=101' target='_blank' style='color:#3a86ff; text-decoration:underline;'>원문 기사 보러가기</a>",
            "source": "네이버 뉴스",
            "image": "images/boar.png",
            "daysAgo": 7,
            "date": "26.02.24",
            "link": "https://n.news.naver.com/mnews/article/056/0012129905?sid=101"
        },
        {
            "id": 14,
            "title": "ASF 20건 중 18건 '해외 유래' 추정…오염 사료 355t 회수·전국 추가 검...",
            "excerpt": "정부가 올해 발생한 아프리카돼지열병(ASF) 유전자 분석 결과를 바탕으로 20건 중 18건이 해외 유래 유형으로... 즉 접경지 야생멧돼지 중심...",
            "body": "네이버 뉴스 검색 결과입니다.<br><br>정부가 올해 발생한 아프리카돼지열병(ASF) 유전자 분석 결과를 바탕으로 20건 중 18건이 해외 유래 유형으로... 즉 접경지 야생멧돼지 중심이었던 과거와 달리 물품·사람·차량 이동 등 인위적 요인에 의해 전국적으로... <br><br><a href='https://n.news.naver.com/mnews/article/003/0013793344?sid=101' target='_blank' style='color:#3a86ff; text-decoration:underline;'>원문 기사 보러가기</a>",
            "source": "네이버 뉴스",
            "image": "images/boar.png",
            "daysAgo": 4,
            "date": "26.02.27",
            "link": "https://n.news.naver.com/mnews/article/003/0013793344?sid=101"
        },
        {
            "id": 15,
            "title": "아프리카돼지열병·조류인플루엔자 살처분 급증...정부,특별방역 연장",
            "excerpt": "아프리카돼지열병(ASF)과 고병원성 조류인플루엔자(AI) 발생에 따른 살처분 규모가 크게 늘고 발병 양상이... 과거 접경지 야생 멧돼지 중심 ...",
            "body": "네이버 뉴스 검색 결과입니다.<br><br>아프리카돼지열병(ASF)과 고병원성 조류인플루엔자(AI) 발생에 따른 살처분 규모가 크게 늘고 발병 양상이... 과거 접경지 야생 멧돼지 중심 확산과 달리, 올해는 전국 곳곳에서 산발적으로 발생하고 있다. 농식품부는... <br><br><a href='https://n.news.naver.com/mnews/article/310/0000134364?sid=102' target='_blank' style='color:#3a86ff; text-decoration:underline;'>원문 기사 보러가기</a>",
            "source": "네이버 뉴스",
            "image": "images/bird_flu.png",
            "daysAgo": 3,
            "date": "26.02.28",
            "link": "https://n.news.naver.com/mnews/article/310/0000134364?sid=102"
        },
        {
            "id": 16,
            "title": "아프리카돼지열병 전수조사 개시…동물진단 옵티팜 수혜 기대",
            "excerpt": "아프리카돼지열병(ASF) 국내 확산 우려가 커지면서 진단 수요 증가로 동물진단업체 옵티팜(153710)의 실적... 제1종 가축전염병인 ASF는...",
            "body": "네이버 뉴스 검색 결과입니다.<br><br>아프리카돼지열병(ASF) 국내 확산 우려가 커지면서 진단 수요 증가로 동물진단업체 옵티팜(153710)의 실적... 제1종 가축전염병인 ASF는 돼지와 멧돼지만 감염되는 바이러스성 출혈성 질병이다. 지난 2019년 9월 경기... <br><br><a href='https://n.news.naver.com/mnews/article/018/0006224050?sid=105' target='_blank' style='color:#3a86ff; text-decoration:underline;'>원문 기사 보러가기</a>",
            "source": "네이버 뉴스",
            "image": "images/boar.png",
            "daysAgo": 6,
            "date": "26.02.25",
            "link": "https://n.news.naver.com/mnews/article/018/0006224050?sid=105"
        },
        {
            "id": 17,
            "title": "연이은 고병원성 AI·ASF에…정부, 특별방역대책 3월까지 연장",
            "excerpt": "올해 ASF 발생은 21건으로 역대 최고치를 기록한 만큼, ASF 방역 조치도 강화된다. 중수본은 \"전국 산발적 발생 양상, 역학적 특성 및 유...",
            "body": "네이버 뉴스 검색 결과입니다.<br><br>올해 ASF 발생은 21건으로 역대 최고치를 기록한 만큼, ASF 방역 조치도 강화된다. 중수본은 \"전국 산발적 발생 양상, 역학적 특성 및 유전형 분석 결과 등을 토대로 현재까지 조사한 결과, 경기 포천 사례 외에는 멧돼지... <br><br><a href='https://n.news.naver.com/mnews/article/421/0008798423?sid=102' target='_blank' style='color:#3a86ff; text-decoration:underline;'>원문 기사 보러가기</a>",
            "source": "네이버 뉴스",
            "image": "images/bird_flu.png",
            "daysAgo": 4,
            "date": "26.02.27",
            "link": "https://n.news.naver.com/mnews/article/421/0008798423?sid=102"
        },
        {
            "id": 18,
            "title": "[혈장단백질 사태] ASF 혈장 오염 충격, 가축방역 전면 재편 불가피",
            "excerpt": "그동안 야생 멧돼지 감염 사례조차 없던 전남 영광·나주, 경남 창녕·의령 등 남부 지역에서도 확진이 이어지며 사실상 전국이 ASF 사정권에 들었...",
            "body": "네이버 뉴스 검색 결과입니다.<br><br>그동안 야생 멧돼지 감염 사례조차 없던 전남 영광·나주, 경남 창녕·의령 등 남부 지역에서도 확진이 이어지며 사실상 전국이 ASF 사정권에 들었다. # 첨가제서 ASF 유전자 첫 검출 방역 당국이 혈장단백질에 주목하기... <br><br><a href='https://www.chukkyung.co.kr/news/articleView.html?idxno=79876' target='_blank' style='color:#3a86ff; text-decoration:underline;'>원문 기사 보러가기</a>",
            "source": "네이버 뉴스",
            "image": "images/boar.png",
            "daysAgo": 4,
            "date": "26.02.27",
            "link": "https://www.chukkyung.co.kr/news/articleView.html?idxno=79876"
        }
    ],
    "ai": [
        {
            "id": 19,
            "title": "경기 포천 산란계 농장서 고병원성 AI…동절기 51건 발생",
            "excerpt": "중수본 관계자는 \"최근 철새 북상 등의 영향으로 경기·강원 지역 야생조류에서 고병원성 조류인플루엔자가 집중적으로 검출되고 있어 해당 지역 오염도...",
            "body": "네이버 뉴스 검색 결과입니다.<br><br>중수본 관계자는 \"최근 철새 북상 등의 영향으로 경기·강원 지역 야생조류에서 고병원성 조류인플루엔자가 집중적으로 검출되고 있어 해당 지역 오염도가 매우 높을 가능성이 있다\"며 \"해당 지방정부는 철새도래지 주변... <br><br><a href='https://n.news.naver.com/mnews/article/001/0015931653?sid=101' target='_blank' style='color:#3a86ff; text-decoration:underline;'>원문 기사 보러가기</a>",
            "source": "네이버 뉴스",
            "image": "images/bird_flu.png",
            "daysAgo": 2,
            "date": "26.03.01",
            "link": "https://n.news.naver.com/mnews/article/001/0015931653?sid=101"
        },
        {
            "id": 20,
            "title": "철원 고병원성 조류인플루엔자 항원 검출… 방역 비상",
            "excerpt": "이에 철원군재난안전대책본부는 23일 긴급회의를 개최하고 야생조류조류 인플루엔자 항원 검출지역 반경 10㎞ 이내 지역을 야생조수 예찰지역으로 지정...",
            "body": "네이버 뉴스 검색 결과입니다.<br><br>이에 철원군재난안전대책본부는 23일 긴급회의를 개최하고 야생조류조류 인플루엔자 항원 검출지역 반경 10㎞ 이내 지역을 야생조수 예찰지역으로 지정하고 두루미탐조관광과 철새먹이주기 행사 등을 통제하기로 했다.... <br><br><a href='https://n.news.naver.com/mnews/article/654/0000167846?sid=102' target='_blank' style='color:#3a86ff; text-decoration:underline;'>원문 기사 보러가기</a>",
            "source": "네이버 뉴스",
            "image": "images/bird_flu.png",
            "daysAgo": 7,
            "date": "26.02.24",
            "link": "https://n.news.naver.com/mnews/article/654/0000167846?sid=102"
        },
        {
            "id": 21,
            "title": "고성에서도 야생조류 ‘고병원성 AI’ 바이러스 검출",
            "excerpt": "앞서 철원에서도 지난 15일과 19일 한탄강변 등에서 수거한 야생조류 폐사체에서 고병원성 조류인플루엔자 바이러스가 확인돼 관광지 임시 폐쇄 등 ...",
            "body": "네이버 뉴스 검색 결과입니다.<br><br>앞서 철원에서도 지난 15일과 19일 한탄강변 등에서 수거한 야생조류 폐사체에서 고병원성 조류인플루엔자 바이러스가 확인돼 관광지 임시 폐쇄 등 대응 조치를 추진 중입니다.<br><br><a href='https://n.news.naver.com/mnews/article/056/0012131280?sid=101' target='_blank' style='color:#3a86ff; text-decoration:underline;'>원문 기사 보러가기</a>",
            "source": "네이버 뉴스",
            "image": "images/bird_flu.png",
            "daysAgo": 6,
            "date": "26.02.25",
            "link": "https://n.news.naver.com/mnews/article/056/0012131280?sid=101"
        },
        {
            "id": 22,
            "title": "고병원성 조류인플루엔자로 폐쇄된 한탄강주상절리길 26일부터 정상 운...",
            "excerpt": "철원군은 야생조류 폐사체에서 고병원성 조류인플루엔자가 확인되자 한탄강주상절리길과 한탄강물윗길, 철원역사문화공원 등 한탄강변 관광지를 폐쇄했다. ...",
            "body": "네이버 뉴스 검색 결과입니다.<br><br>철원군은 야생조류 폐사체에서 고병원성 조류인플루엔자가 확인되자 한탄강주상절리길과 한탄강물윗길, 철원역사문화공원 등 한탄강변 관광지를 폐쇄했다. 이에 지역 내 음식점과 숙박업소 등 단체예약이 취소되는 등... <br><br><a href='https://n.news.naver.com/mnews/article/087/0001176505?sid=102' target='_blank' style='color:#3a86ff; text-decoration:underline;'>원문 기사 보러가기</a>",
            "source": "네이버 뉴스",
            "image": "images/bird_flu.png",
            "daysAgo": 5,
            "date": "26.02.26",
            "link": "https://n.news.naver.com/mnews/article/087/0001176505?sid=102"
        },
        {
            "id": 23,
            "title": "포천 산란계 농장서 고병원성 AI 확진… 중수본 방역 관리 강화",
            "excerpt": "최근 철새 북상 시기와 맞물리며 경기ㆍ강원 등 북부 지역을 중심으로 야생조류에서 고병원성 조류인플루엔자 검출 사례가 이어지고 있다. 중수본은 H...",
            "body": "네이버 뉴스 검색 결과입니다.<br><br>최근 철새 북상 시기와 맞물리며 경기ㆍ강원 등 북부 지역을 중심으로 야생조류에서 고병원성 조류인플루엔자 검출 사례가 이어지고 있다. 중수본은 H5형 항원이 확인된 직후 '조류인플루엔자 긴급행동지침(SOP)'에... <br><br><a href='http://www.youngnong.co.kr/news/articleView.html?idxno=57813' target='_blank' style='color:#3a86ff; text-decoration:underline;'>원문 기사 보러가기</a>",
            "source": "네이버 뉴스",
            "image": "images/bird_flu.png",
            "daysAgo": 1,
            "date": "26.03.02",
            "link": "http://www.youngnong.co.kr/news/articleView.html?idxno=57813"
        },
        {
            "id": 24,
            "title": "성주 닭농장 조류AI 항원 검출…경북도, 25만마리 살처분",
            "excerpt": "이번 겨울 들어 현재까지 전국 고병원성 조류인플루엔자 발생은 가금농장 46건, 야생조류 52건이다. 가금농장 발생 가운데 경북은 3건, 경기와 ...",
            "body": "네이버 뉴스 검색 결과입니다.<br><br>이번 겨울 들어 현재까지 전국 고병원성 조류인플루엔자 발생은 가금농장 46건, 야생조류 52건이다. 가금농장 발생 가운데 경북은 3건, 경기와 충북, 전남, 충남 각 9건, 전북 4건, 경남, 세종, 광주 각 1건씩이다. 박찬국... <br><br><a href='https://n.news.naver.com/mnews/article/003/0013785043?sid=102' target='_blank' style='color:#3a86ff; text-decoration:underline;'>원문 기사 보러가기</a>",
            "source": "네이버 뉴스",
            "image": "images/bird_flu.png",
            "daysAgo": 7,
            "date": "26.02.24",
            "link": "https://n.news.naver.com/mnews/article/003/0013785043?sid=102"
        },
        {
            "id": 25,
            "title": "ASF·구제역·AI 3중고, 특별방역기간 3월말까지 연장",
            "excerpt": "고병원성 조류인플루엔자(AI)가 추가 발생했다.3대 재난형 가축전염병 발생이 이어지는 삼중고 속에... 고병원성 AI는 25/26 동절기 들어 ...",
            "body": "네이버 뉴스 검색 결과입니다.<br><br>고병원성 조류인플루엔자(AI)가 추가 발생했다.3대 재난형 가축전염병 발생이 이어지는 삼중고 속에... 고병원성 AI는 25/26 동절기 들어 전년 시즌 대비 고병원성 AI 발생 시군수와 야생조류 검출 건수·지역이 모두... <br><br><a href='https://www.dailyvet.co.kr/news/prevention-hygiene/275036' target='_blank' style='color:#3a86ff; text-decoration:underline;'>원문 기사 보러가기</a>",
            "source": "네이버 뉴스",
            "image": "images/bird_flu.png",
            "daysAgo": 0,
            "date": "26.03.03",
            "link": "https://www.dailyvet.co.kr/news/prevention-hygiene/275036"
        },
        {
            "id": 26,
            "title": "AI 이어 ASF 까지 덮친 철원…지역경제 타격 불가피",
            "excerpt": "ASF 확산 방지를 위해 차단 방역에 총력을 기울이고 있다\"며 \"정밀검사 결과에 따라 관광지 운영 재개 여부를 신중히 검토하겠다\"고 말했다. 이...",
            "body": "네이버 뉴스 검색 결과입니다.<br><br>ASF 확산 방지를 위해 차단 방역에 총력을 기울이고 있다\"며 \"정밀검사 결과에 따라 관광지 운영 재개 여부를 신중히 검토하겠다\"고 말했다. 이재용 기자 #지역경제 #철원군 #관광지 #야생조류 #조류인플루엔자<br><br><a href='https://n.news.naver.com/mnews/article/654/0000168020?sid=102' target='_blank' style='color:#3a86ff; text-decoration:underline;'>원문 기사 보러가기</a>",
            "source": "네이버 뉴스",
            "image": "images/bird_flu.png",
            "daysAgo": 6,
            "date": "26.02.25",
            "link": "https://n.news.naver.com/mnews/article/654/0000168020?sid=102"
        },
        {
            "id": 27,
            "title": "철원, 야생조류 ‘고병원성 AI’ 검출…관광지 폐쇄",
            "excerpt": "국립야생동물질병관리원은 이달(2월) 15일과 19일, 한탄강변과 철원평야에서 수거한 야생조류 폐사체 4마리에서 H5N1(에이치-파이브-엔-원)형...",
            "body": "네이버 뉴스 검색 결과입니다.<br><br>국립야생동물질병관리원은 이달(2월) 15일과 19일, 한탄강변과 철원평야에서 수거한 야생조류 폐사체 4마리에서 H5N1(에이치-파이브-엔-원)형 고병원성 조류인플루엔자 바이러스가 검출됐다고 밝혔습니다. 이에 따라... <br><br><a href='https://n.news.naver.com/mnews/article/056/0012130363?sid=101' target='_blank' style='color:#3a86ff; text-decoration:underline;'>원문 기사 보러가기</a>",
            "source": "네이버 뉴스",
            "image": "images/bird_flu.png",
            "daysAgo": 7,
            "date": "26.02.24",
            "link": "https://n.news.naver.com/mnews/article/056/0012130363?sid=101"
        },
        {
            "id": 28,
            "title": "경남도 철새 북상…조류AI 농장 유입 차단 당부",
            "excerpt": "/경남도 경남도는 전국 가금농가에서 고병원성 조류인플루엔자(AI)가 지속 발생하는 엄중한 상황 속에서... 경남에서는 이달 6일 거창 종오리 농...",
            "body": "네이버 뉴스 검색 결과입니다.<br><br>/경남도 경남도는 전국 가금농가에서 고병원성 조류인플루엔자(AI)가 지속 발생하는 엄중한 상황 속에서... 경남에서는 이달 6일 거창 종오리 농장 발생 이후 추가 발생은 없으나, 창원·거창·합천 지역 야생조류에서 총... <br><br><a href='http://www.gndomin.com/news/articleView.html?idxno=466470' target='_blank' style='color:#3a86ff; text-decoration:underline;'>원문 기사 보러가기</a>",
            "source": "네이버 뉴스",
            "image": "images/bird_flu.png",
            "daysAgo": 6,
            "date": "26.02.25",
            "link": "http://www.gndomin.com/news/articleView.html?idxno=466470"
        }
    ],
    "ecosystem": [
        {
            "id": 29,
            "title": "헌정회-전남도, 외래어종 퇴치 맞손 생태계 복원·농촌 일자리 창출 협...",
            "excerpt": "이번 협약은 정대철 회장 취임 이후 추진 중인 ‘외래어종 퇴치를 통한 생태계 복원 및 농촌 살리기 운동’의 일환이다. 현재 국내 하천에서는 큰입...",
            "body": "네이버 뉴스 검색 결과입니다.<br><br>이번 협약은 정대철 회장 취임 이후 추진 중인 ‘외래어종 퇴치를 통한 생태계 복원 및 농촌 살리기 운동’의 일환이다. 현재 국내 하천에서는 큰입배스, 블루길, 붉은귀거북, 황소개구리 등 포식성 외래어종이 토종 치어와... <br><br><a href='http://www.shinailbo.co.kr/news/articleView.html?idxno=2196814' target='_blank' style='color:#3a86ff; text-decoration:underline;'>원문 기사 보러가기</a>",
            "source": "네이버 뉴스",
            "image": "images/bullfrog.png",
            "daysAgo": 4,
            "date": "26.02.27",
            "link": "http://www.shinailbo.co.kr/news/articleView.html?idxno=2196814"
        }
    ],
    "association": [
        {
            "id": 30,
            "title": "야생생물관리협회 예천지회, 예천군에 고향사랑기부금 기탁",
            "excerpt": "야생생물관리협회 예천지회(회장 김정규)가 26일 예천군청을 방문, 고향사랑기부금 300만 원을 김학동 군수를 통해 지정 기탁했다. 김학동 군수는...",
            "body": "네이버 뉴스 검색 결과입니다.<br><br>야생생물관리협회 예천지회(회장 김정규)가 26일 예천군청을 방문, 고향사랑기부금 300만 원을 김학동 군수를 통해 지정 기탁했다. 김학동 군수는 \"야생생물관리협회 예천지회 회원과 가족분들의 따뜻한 관심과 지원에... <br><br><a href='https://www.dkilbo.com/news/articleView.html?idxno=535107' target='_blank' style='color:#3a86ff; text-decoration:underline;'>원문 기사 보러가기</a>",
            "source": "네이버 뉴스",
            "image": "images/env_gov.png",
            "daysAgo": 5,
            "date": "26.02.26",
            "link": "https://www.dkilbo.com/news/articleView.html?idxno=535107"
        },
        {
            "id": 31,
            "title": "[현장속으로]열 걸음마다 철제 올무...죽음 위기 내몰린 야생동물들",
            "excerpt": "야생생물관리협회 관계자는 \"이런 매듭은 몸이 잘리지 않는 한 동물이 스스로 풀 수 없다\"며 \"전국이 올무로 뒤덮였다고 해도 과언이 아닐 정도\"라...",
            "body": "네이버 뉴스 검색 결과입니다.<br><br>야생생물관리협회 관계자는 \"이런 매듭은 몸이 잘리지 않는 한 동물이 스스로 풀 수 없다\"며 \"전국이 올무로 뒤덮였다고 해도 과언이 아닐 정도\"라고 말했다. 이날 영산강유역환경청은 장성군 내 한 야산에서 불법 엽구... <br><br><a href='https://www.namdonews.com/news/articleView.html?idxno=902438' target='_blank' style='color:#3a86ff; text-decoration:underline;'>원문 기사 보러가기</a>",
            "source": "네이버 뉴스",
            "image": "images/env_gov.png",
            "daysAgo": 6,
            "date": "26.02.25",
            "link": "https://www.namdonews.com/news/articleView.html?idxno=902438"
        }
    ],
    "editorial": [
        {
            "id": 32,
            "title": "[기고] 산림청 부여국유림관리소 이상필 소장",
            "excerpt": "야생동물의 서식지는 파괴되고, 인근 주민의 삶의 터전도 위협받습니다. 관광ㆍ임업 등 지역 기반 산업에도 막대한 피해가 발생합니다. 무엇보다 산불...",
            "body": "네이버 뉴스 검색 결과입니다.<br><br>야생동물의 서식지는 파괴되고, 인근 주민의 삶의 터전도 위협받습니다. 관광ㆍ임업 등 지역 기반 산업에도 막대한 피해가 발생합니다. 무엇보다 산불 진화 과정에서 소중한 인명 피해가 발생할 수 있다는 점은 우리가... <br><br><a href='http://www.youngnong.co.kr/news/articleView.html?idxno=57711' target='_blank' style='color:#3a86ff; text-decoration:underline;'>원문 기사 보러가기</a>",
            "source": "네이버 뉴스",
            "image": "images/env_gov.png",
            "daysAgo": 6,
            "date": "26.02.25",
            "link": "http://www.youngnong.co.kr/news/articleView.html?idxno=57711"
        }
    ]
}