{
    "hunting": [
        {
            "id": 2,
            "title": "부안군, 파종기 대비 유해야생동물 기동포획단 간담회 개최",
            "excerpt": "이번 간담회는 유해야생동물 기동포획단과 관계 공무원 등이 참석한 가운데 진행됐으며 파종기를 앞두고 증가하는 야생동물로 인한 농작물 피해를 예방하...",
            "body": "네이버 뉴스 검색 결과입니다.<br><br>이번 간담회는 유해야생동물 기동포획단과 관계 공무원 등이 참석한 가운데 진행됐으며 파종기를 앞두고 증가하는 야생동물로 인한 농작물 피해를 예방하고 기동포획단의 안전한 활동을 지원하기 위해 마련됐다. 특히... <br><br><a href='http://sjbnews.com/news/news.php?number=873376' target='_blank' style='color:#3a86ff; text-decoration:underline;'>원문 기사 보러가기</a>",
            "source": "네이버 뉴스",
            "image": "images/hunter.png",
            "daysAgo": 1,
            "date": "26.03.10",
            "link": "http://sjbnews.com/news/news.php?number=873376"
        },
        {
            "id": 3,
            "title": "세종시, 유해 야생동물 일제 포획",
            "excerpt": "세종시가 오늘까지 원수산과 전월산, 읍면 지역에서, 유해 야생동물을 일제 포획합니다. 시는 농작물 피해를 막고, 시민들의 안전을 보호하기 위해 ...",
            "body": "네이버 뉴스 검색 결과입니다.<br><br>세종시가 오늘까지 원수산과 전월산, 읍면 지역에서, 유해 야생동물을 일제 포획합니다. 시는 농작물 피해를 막고, 시민들의 안전을 보호하기 위해 포획 활동을 벌이고, 포획한 멧돼지를 대상으로 아프리카돼지열병 등을... <br><br><a href='https://tjmbc.co.kr/NewsArticle/828433' target='_blank' style='color:#3a86ff; text-decoration:underline;'>원문 기사 보러가기</a>",
            "source": "네이버 뉴스",
            "image": "images/boar.png",
            "daysAgo": 2,
            "date": "26.03.09",
            "link": "https://tjmbc.co.kr/NewsArticle/828433"
        },
        {
            "id": 4,
            "title": "[단독] 멧돼지는 살리고 농가는 죽이고…'야생동물기피제'가 사라진다",
            "excerpt": "철거된 빈자리는 야생동물 기피제와 위성항법장치(GPS) 포획트랩 등으로 메우겠다는 방침이다. 하지만 정작 방역 현장에서 가장 핵심적인 역할을 해...",
            "body": "네이버 뉴스 검색 결과입니다.<br><br>철거된 빈자리는 야생동물 기피제와 위성항법장치(GPS) 포획트랩 등으로 메우겠다는 방침이다. 하지만 정작 방역 현장에서 가장 핵심적인 역할을 해야 할 야동물기피제가 현실과 동떨어진 불합리한 규제 장벽에 막혀... <br><br><a href='https://n.news.naver.com/mnews/article/088/0000999799?sid=102' target='_blank' style='color:#3a86ff; text-decoration:underline;'>원문 기사 보러가기</a>",
            "source": "네이버 뉴스",
            "image": "images/boar.png",
            "daysAgo": 5,
            "date": "26.03.06",
            "link": "https://n.news.naver.com/mnews/article/088/0000999799?sid=102"
        },
        {
            "id": 5,
            "title": "설악산 야생동물 노린 덫 17점 수거…불법 엽구 서리 횡행",
            "excerpt": "국립공원 내에서 야생동물을 불법 포획하거나 엽구를 설치할 경우 자연공원법에 따라 3년 이하의 징역 또는 3000만 원 이하의 벌금에 처해질 수 ...",
            "body": "네이버 뉴스 검색 결과입니다.<br><br>국립공원 내에서 야생동물을 불법 포획하거나 엽구를 설치할 경우 자연공원법에 따라 3년 이하의 징역 또는 3000만 원 이하의 벌금에 처해질 수 있다. 설악산국립공원사무소는 야생동물 서식지 보호를 위해 앞으로도... <br><br><a href='https://n.news.naver.com/mnews/article/421/0008811104?sid=102' target='_blank' style='color:#3a86ff; text-decoration:underline;'>원문 기사 보러가기</a>",
            "source": "네이버 뉴스",
            "image": "images/hunter.png",
            "daysAgo": 5,
            "date": "26.03.06",
            "link": "https://n.news.naver.com/mnews/article/421/0008811104?sid=102"
        },
        {
            "id": 6,
            "title": "불법 포획한 기러기 논에 매달아 둔 50대…야생동물보호법 위반 조사",
            "excerpt": "이 남성은 어제(3일) 오전 11시쯤 군산시 옥서면 자신의 논에서 포획한 기러기 6마리를 쇠막대기에 매달아 놓은 혐의를 받고 있다. 경찰은 남성...",
            "body": "네이버 뉴스 검색 결과입니다.<br><br>이 남성은 어제(3일) 오전 11시쯤 군산시 옥서면 자신의 논에서 포획한 기러기 6마리를 쇠막대기에 매달아 놓은 혐의를 받고 있다. 경찰은 남성을 야생동물보호법 위반 혐의로 입건해 정확한 사건 경위를 조사하고 있다.<br><br><a href='https://n.news.naver.com/mnews/article/448/0000594304?sid=102' target='_blank' style='color:#3a86ff; text-decoration:underline;'>원문 기사 보러가기</a>",
            "source": "네이버 뉴스",
            "image": "images/police.png",
            "daysAgo": 7,
            "date": "26.03.04",
            "link": "https://n.news.naver.com/mnews/article/448/0000594304?sid=102"
        },
        {
            "id": 7,
            "title": "사천시, 유해야생동물 수확기 피해방지단 가동",
            "excerpt": "이들은 멧돼지와 고라니 등 유해야생동물 포획 활동을 통해 농작물 피해를 최소화하고 아프리카돼지열병 확산 방지에 기여하게 된다. 시는 효과적인 유...",
            "body": "네이버 뉴스 검색 결과입니다.<br><br>이들은 멧돼지와 고라니 등 유해야생동물 포획 활동을 통해 농작물 피해를 최소화하고 아프리카돼지열병 확산 방지에 기여하게 된다. 시는 효과적인 유해야생동물 포획 활동을 지원하기 위해 포획 보상금은 물론... <br><br><a href='https://www.newsgn.com/news/articleView.html?idxno=538207' target='_blank' style='color:#3a86ff; text-decoration:underline;'>원문 기사 보러가기</a>",
            "source": "네이버 뉴스",
            "image": "images/boar.png",
            "daysAgo": 6,
            "date": "26.03.05",
            "link": "https://www.newsgn.com/news/articleView.html?idxno=538207"
        },
        {
            "id": 8,
            "title": "'혹시 마지막?'…유해야생동물의 봄나들이",
            "excerpt": "지난해 12월 유해야생동물로 지정돼 지자체의 포획이 가능해진 꽃사슴 무리가 4일 제주시 용강동 제주마방목지에서 활동하고 있다. 꽃사슴에 대한 유...",
            "body": "네이버 뉴스 검색 결과입니다.<br><br>지난해 12월 유해야생동물로 지정돼 지자체의 포획이 가능해진 꽃사슴 무리가 4일 제주시 용강동 제주마방목지에서 활동하고 있다. 꽃사슴에 대한 유해야생동물 지정과 이어질 지자체의 포획·사살이 적절한지에... <br><br><a href='https://n.news.naver.com/mnews/article/001/0015937113?sid=103' target='_blank' style='color:#3a86ff; text-decoration:underline;'>원문 기사 보러가기</a>",
            "source": "네이버 뉴스",
            "image": "images/env_gov.png",
            "daysAgo": 7,
            "date": "26.03.04",
            "link": "https://n.news.naver.com/mnews/article/001/0015937113?sid=103"
        },
        {
            "id": 9,
            "title": "음성 유기 동물 1천 마리?…4년 새 3배 폭증 '기현상'",
            "excerpt": "5일 충청북도와 음성군에 따르면 지난해 음성지역에서 포획된 유기동물은 모두 992마리다. 개 723마리... 음성군은 야산을 중심으로 들개 등 ...",
            "body": "네이버 뉴스 검색 결과입니다.<br><br>5일 충청북도와 음성군에 따르면 지난해 음성지역에서 포획된 유기동물은 모두 992마리다. 개 723마리... 음성군은 야산을 중심으로 들개 등 야생화된 동물 번식이 늘어난 영향으로 보고 있다. 음성군 관계자는 \"들개가... <br><br><a href='https://n.news.naver.com/mnews/article/079/0004121698?sid=102' target='_blank' style='color:#3a86ff; text-decoration:underline;'>원문 기사 보러가기</a>",
            "source": "네이버 뉴스",
            "image": "images/hunter.png",
            "daysAgo": 6,
            "date": "26.03.05",
            "link": "https://n.news.naver.com/mnews/article/079/0004121698?sid=102"
        },
        {
            "id": 10,
            "title": "고흥군, 섬 지역 유해야생동물 대응 강화…시산도서 합동 포획 활동",
            "excerpt": "고흥군(군수 공영민)은 지난 3일부터 4일까지 이틀간 도양읍 시산도 일대에서 유해야생동물 피해방지단과 민간 환경단체가 함께 참여한 가운데 불법 ...",
            "body": "네이버 뉴스 검색 결과입니다.<br><br>고흥군(군수 공영민)은 지난 3일부터 4일까지 이틀간 도양읍 시산도 일대에서 유해야생동물 피해방지단과 민간 환경단체가 함께 참여한 가운데 불법 엽구 수거와 유해야생동물 포획 활동을 실시했다고 밝혔다. 이번 활동은... <br><br><a href='https://www.thefairnews.co.kr/news/articleView.html?idxno=70735' target='_blank' style='color:#3a86ff; text-decoration:underline;'>원문 기사 보러가기</a>",
            "source": "네이버 뉴스",
            "image": "images/hunter.png",
            "daysAgo": 6,
            "date": "26.03.05",
            "link": "https://www.thefairnews.co.kr/news/articleView.html?idxno=70735"
        }
    ],
    "asf": [
        {
            "id": 12,
            "title": "경산시, '드론 활용' 아프리카돼지열병 차단 방역 강화",
            "excerpt": "소독약품과 멧돼지 기피제를 집중 살포했다. 이와 관련 조현일 경산시장은 이날 방역 현장을 직접 방문해 추진 상황을 점검하고, 현장 대응 체계를 ...",
            "body": "네이버 뉴스 검색 결과입니다.<br><br>소독약품과 멧돼지 기피제를 집중 살포했다. 이와 관련 조현일 경산시장은 이날 방역 현장을 직접 방문해 추진 상황을 점검하고, 현장 대응 체계를 살폈다. 방역 현장에서 조현일 경산시장은 \"아프리카돼지열병은 한 번... <br><br><a href='https://www.agrinet.co.kr/news/articleView.html?idxno=402400' target='_blank' style='color:#3a86ff; text-decoration:underline;'>원문 기사 보러가기</a>",
            "source": "네이버 뉴스",
            "image": "images/boar.png",
            "daysAgo": 2,
            "date": "26.03.09",
            "link": "https://www.agrinet.co.kr/news/articleView.html?idxno=402400"
        },
        {
            "id": 13,
            "title": "‘아프리카돼지열병’ 확산…‘사료 감염’ 가능성에 혼란",
            "excerpt": "정부의 역학조사 결과, 새끼 돼지 사료의 원료인 '돼지 혈장 단백질' 시료에서 아프리카돼지열병 유전체가 검출됐습니다. 사료에 의한 감염 가능성이...",
            "body": "네이버 뉴스 검색 결과입니다.<br><br>정부의 역학조사 결과, 새끼 돼지 사료의 원료인 '돼지 혈장 단백질' 시료에서 아프리카돼지열병 유전체가 검출됐습니다. 사료에 의한 감염 가능성이 현실로 나타난 겁니다. 멧돼지를 감염원으로 보고 방역 시설을... <br><br><a href='https://n.news.naver.com/mnews/article/056/0012135662?sid=101' target='_blank' style='color:#3a86ff; text-decoration:underline;'>원문 기사 보러가기</a>",
            "source": "네이버 뉴스",
            "image": "images/boar.png",
            "daysAgo": 6,
            "date": "26.03.05",
            "link": "https://n.news.naver.com/mnews/article/056/0012135662?sid=101"
        },
        {
            "id": 14,
            "title": "현장 돼지수의사가 발견한 당진 ASF, 올해 발생 바이러스와 99.99% 동일",
            "excerpt": "지난해 11월 당진 돼지농장에서 발생한 아프리카돼지열병(ASF)은 일선 돼지수의사에 의해 포착됐다.당시... 경기도 포천에서 발생한 2건만 기존...",
            "body": "네이버 뉴스 검색 결과입니다.<br><br>지난해 11월 당진 돼지농장에서 발생한 아프리카돼지열병(ASF)은 일선 돼지수의사에 의해 포착됐다.당시... 경기도 포천에서 발생한 2건만 기존 국내 멧돼지에서 지배적으로 유행해 온 IGR-II로 판명됐다.방역당국은... <br><br><a href='https://www.dailyvet.co.kr/news/association/275325' target='_blank' style='color:#3a86ff; text-decoration:underline;'>원문 기사 보러가기</a>",
            "source": "네이버 뉴스",
            "image": "images/boar.png",
            "daysAgo": 7,
            "date": "26.03.04",
            "link": "https://www.dailyvet.co.kr/news/association/275325"
        },
        {
            "id": 15,
            "title": "연천군, 아프리카돼지열병(ASF) 확산 차단 총력 대응",
            "excerpt": "▲연천, 아프리카돼지열병(ASF) 초동방역, 확산 차단 총력<사진제공=연천군> 연천군은 지난 4일 관내... 발생 농장 반경 내 농가에 대한 이...",
            "body": "네이버 뉴스 검색 결과입니다.<br><br>▲연천, 아프리카돼지열병(ASF) 초동방역, 확산 차단 총력<사진제공=연천군> 연천군은 지난 4일 관내... 발생 농장 반경 내 농가에 대한 이동 제한과 임상 예찰을 강화하고, 야생 멧돼지를 통한 추가 전파를 차단하기 위해... <br><br><a href='https://www.gukjenews.com/news/articleView.html?idxno=3521237' target='_blank' style='color:#3a86ff; text-decoration:underline;'>원문 기사 보러가기</a>",
            "source": "네이버 뉴스",
            "image": "images/boar.png",
            "daysAgo": 5,
            "date": "26.03.06",
            "link": "https://www.gukjenews.com/news/articleView.html?idxno=3521237"
        },
        {
            "id": 16,
            "title": "연천군 소재 돼지농가 ASF 확진…출입통제-살처분 등 긴급 방역",
            "excerpt": "돼지농가에서 아프리카돼지열병(ASF)이 확진되자 즉시 초동 방역 조치를 시행하고 확산 차단에 나섰다. 해당... 야생 멧돼지를 통한 추가 전파를...",
            "body": "네이버 뉴스 검색 결과입니다.<br><br>돼지농가에서 아프리카돼지열병(ASF)이 확진되자 즉시 초동 방역 조치를 시행하고 확산 차단에 나섰다. 해당... 야생 멧돼지를 통한 추가 전파를 막기 위해 울타리 점검도 병행하고 있다. 연천군 관계 부서 공무원들은 발생... <br><br><a href='https://www.cnbnews.com/news/article.html?no=782307' target='_blank' style='color:#3a86ff; text-decoration:underline;'>원문 기사 보러가기</a>",
            "source": "네이버 뉴스",
            "image": "images/boar.png",
            "daysAgo": 2,
            "date": "26.03.09",
            "link": "https://www.cnbnews.com/news/article.html?no=782307"
        },
        {
            "id": 17,
            "title": "연천군, 돼지농가 ASF 확진…초동 방역·확산 차단",
            "excerpt": "경기 연천군이 관내 돼지농가에서 아프리카돼지열병(ASF)이 발생함에 따라 초동 방역 조치를 시행하고 확산... 또 농가 진입로에 통제초소를 설치...",
            "body": "네이버 뉴스 검색 결과입니다.<br><br>경기 연천군이 관내 돼지농가에서 아프리카돼지열병(ASF)이 발생함에 따라 초동 방역 조치를 시행하고 확산... 또 농가 진입로에 통제초소를 설치해 축산 차량과 관계자에 대한 소독을 실시하고 있으며 야생 멧돼지를... <br><br><a href='http://www.shinailbo.co.kr/news/articleView.html?idxno=2198922' target='_blank' style='color:#3a86ff; text-decoration:underline;'>원문 기사 보러가기</a>",
            "source": "네이버 뉴스",
            "image": "images/boar.png",
            "daysAgo": 6,
            "date": "26.03.05",
            "link": "http://www.shinailbo.co.kr/news/articleView.html?idxno=2198922"
        },
        {
            "id": 18,
            "title": "한돈협 제기 '혈장단백 사료' ASF 오염원 규명 퍼즐 완성...100% '일치'",
            "excerpt": "올해 양돈업계를 뒤흔들었던 ASF발생과 관련해 대한한돈협회가 처음 제기한 자돈 사료 내 혈장단백질 오염... 당초 고온 처리 과정을 거치는 혈장...",
            "body": "네이버 뉴스 검색 결과입니다.<br><br>올해 양돈업계를 뒤흔들었던 ASF발생과 관련해 대한한돈협회가 처음 제기한 자돈 사료 내 혈장단백질 오염... 당초 고온 처리 과정을 거치는 혈장 단백에서의 감염은 있을 수 없다는 사료업계의 주장과 야생 멧돼지에서... <br><br><a href='https://www.farminsight.net/news/articleView.html?idxno=16096' target='_blank' style='color:#3a86ff; text-decoration:underline;'>원문 기사 보러가기</a>",
            "source": "네이버 뉴스",
            "image": "images/boar.png",
            "daysAgo": 1,
            "date": "26.03.10",
            "link": "https://www.farminsight.net/news/articleView.html?idxno=16096"
        },
        {
            "id": 19,
            "title": "경산시, 드론 활용해 ASF 선제 차단 방역 강화",
            "excerpt": "▲ 경산시는 아프리카돼지열병(ASF)에 대비, 바이러스의 농가 유입을 원천 차단하기 위해 드론을 활용한... 이날 드론 2대를 투입해 기존 소독...",
            "body": "네이버 뉴스 검색 결과입니다.<br><br>▲ 경산시는 아프리카돼지열병(ASF)에 대비, 바이러스의 농가 유입을 원천 차단하기 위해 드론을 활용한... 이날 드론 2대를 투입해 기존 소독 차량의 접근이 어려웠던 축사 지붕과 농장 주변, 야생 멧돼지 출현이 우려되는... <br><br><a href='https://www.dkilbo.com/news/articleView.html?idxno=536165' target='_blank' style='color:#3a86ff; text-decoration:underline;'>원문 기사 보러가기</a>",
            "source": "네이버 뉴스",
            "image": "images/boar.png",
            "daysAgo": 3,
            "date": "26.03.08",
            "link": "https://www.dkilbo.com/news/articleView.html?idxno=536165"
        },
        {
            "id": 20,
            "title": "사료서 ASF 유전자 나와 양돈업계 ‘충격’",
            "excerpt": "조호성 전북대학교 수의과대학 교수는 “올해 ASF 발생은 최대 3주까지 이어지는 조용한 잠복기와 발생지역에 야생멧돼지 양성 위험이 낮았던 것이 ...",
            "body": "네이버 뉴스 검색 결과입니다.<br><br>조호성 전북대학교 수의과대학 교수는 “올해 ASF 발생은 최대 3주까지 이어지는 조용한 잠복기와 발생지역에 야생멧돼지 양성 위험이 낮았던 것이 오히려 (원인 규명에선) 함정이었다”고 말했다. 그러면서... <br><br><a href='https://n.news.naver.com/mnews/article/662/0000089690?sid=101' target='_blank' style='color:#3a86ff; text-decoration:underline;'>원문 기사 보러가기</a>",
            "source": "네이버 뉴스",
            "image": "images/boar.png",
            "daysAgo": 7,
            "date": "26.03.04",
            "link": "https://n.news.naver.com/mnews/article/662/0000089690?sid=101"
        },
        {
            "id": 21,
            "title": "경산시, ASF 차단 총력…드론 투입 ‘고강도 방역’",
            "excerpt": "소독약품과 멧돼지 기피제를 집중 살포했다. 경산시는 드론 방역을 통해 차량 방역의 사각지대를 해소하고, ASF 전파 가능성이 높은 지역을 선제적...",
            "body": "네이버 뉴스 검색 결과입니다.<br><br>소독약품과 멧돼지 기피제를 집중 살포했다. 경산시는 드론 방역을 통해 차량 방역의 사각지대를 해소하고, ASF 전파 가능성이 높은 지역을 선제적으로 관리한다는 방침이다. 조현일 경산시장은 이날 방역 현장을 직접... <br><br><a href='https://n.news.naver.com/mnews/article/031/0001010721?sid=102' target='_blank' style='color:#3a86ff; text-decoration:underline;'>원문 기사 보러가기</a>",
            "source": "네이버 뉴스",
            "image": "images/boar.png",
            "daysAgo": 6,
            "date": "26.03.05",
            "link": "https://n.news.naver.com/mnews/article/031/0001010721?sid=102"
        }
    ],
    "ai": [
        {
            "id": 22,
            "title": "AI 발생농장 '방역 미흡' 잇단 적발…정부 \"보상금 감액 등 엄격 조치\"",
            "excerpt": "정부가 이번 겨울 고병원성 조류인플루엔자(AI)가 발생한 가금농장에서 다수의 방역 미흡 사례가 확인됨에... 이번 2025~2026년 동절기 동...",
            "body": "네이버 뉴스 검색 결과입니다.<br><br>정부가 이번 겨울 고병원성 조류인플루엔자(AI)가 발생한 가금농장에서 다수의 방역 미흡 사례가 확인됨에... 이번 2025~2026년 동절기 동안 가금농장에서는 53건, 야생조류에서는 62건의 고병원성 AI가 발생했다.... <br><br><a href='https://n.news.naver.com/mnews/article/003/0013810051?sid=101' target='_blank' style='color:#3a86ff; text-decoration:underline;'>원문 기사 보러가기</a>",
            "source": "네이버 뉴스",
            "image": "images/bird_flu.png",
            "daysAgo": 2,
            "date": "26.03.09",
            "link": "https://n.news.naver.com/mnews/article/003/0013810051?sid=101"
        },
        {
            "id": 23,
            "title": "아산 메추리농장·김제 육용종계 농장서 고병원성 AI",
            "excerpt": "고병원성 조류인플루엔자 감염 여부를 확인할 예정이다. 또 전국 육용종계 농장 223곳을 대상으로 오는 14일까지 매일 전화 예찰을 진행하고, 2...",
            "body": "네이버 뉴스 검색 결과입니다.<br><br>고병원성 조류인플루엔자 감염 여부를 확인할 예정이다. 또 전국 육용종계 농장 223곳을 대상으로 오는 14일까지 매일 전화 예찰을 진행하고, 20일까지 방역 점검을 실시할 계획이다. 중수본 관계자는 \"야생조류가... <br><br><a href='https://n.news.naver.com/mnews/article/001/0015950791?sid=101' target='_blank' style='color:#3a86ff; text-decoration:underline;'>원문 기사 보러가기</a>",
            "source": "네이버 뉴스",
            "image": "images/bird_flu.png",
            "daysAgo": 1,
            "date": "26.03.10",
            "link": "https://n.news.naver.com/mnews/article/001/0015950791?sid=101"
        },
        {
            "id": 24,
            "title": "‘차단방역 미흡 엄단’과 ‘징벌적 보상금 삭감’ 고병원성 AI 방역 시...",
            "excerpt": "최근에도 발생 추세가 꺾이지 않고 있고, 3월 이후 철새 북상시기에 위험도가 높아질 수 있다는 것이다.농림축산식품부 이동식 방역정책국장(CVO)...",
            "body": "네이버 뉴스 검색 결과입니다.<br><br>최근에도 발생 추세가 꺾이지 않고 있고, 3월 이후 철새 북상시기에 위험도가 높아질 수 있다는 것이다.농림축산식품부 이동식 방역정책국장(CVO)은 “현재 야생조류에서 지속적으로 고병원성 조류인플루엔자... <br><br><a href='https://www.dailyvet.co.kr/news/prevention-hygiene/276024' target='_blank' style='color:#3a86ff; text-decoration:underline;'>원문 기사 보러가기</a>",
            "source": "네이버 뉴스",
            "image": "images/bird_flu.png",
            "daysAgo": 0,
            "date": "26.03.11",
            "link": "https://www.dailyvet.co.kr/news/prevention-hygiene/276024"
        },
        {
            "id": 25,
            "title": "포천 또 AI 발생…가금 농가 밀집 지역 방역 비상",
            "excerpt": "포천 창수면에서 또다시 고병원성 조류인플루엔자(AI)가 발생하면서 가금 사육 구조와 방역 체계 전반을... 않아 야생조류 접근을 완전히 차단하기...",
            "body": "네이버 뉴스 검색 결과입니다.<br><br>포천 창수면에서 또다시 고병원성 조류인플루엔자(AI)가 발생하면서 가금 사육 구조와 방역 체계 전반을... 않아 야생조류 접근을 완전히 차단하기 어려운 실정이라는 지적이다. 실제로 포천시는 이러한 위험성을... <br><br><a href='https://n.news.naver.com/mnews/article/666/0000098385?sid=102' target='_blank' style='color:#3a86ff; text-decoration:underline;'>원문 기사 보러가기</a>",
            "source": "네이버 뉴스",
            "image": "images/bird_flu.png",
            "daysAgo": 4,
            "date": "26.03.07",
            "link": "https://n.news.naver.com/mnews/article/666/0000098385?sid=102"
        },
        {
            "id": 26,
            "title": "AI·ASF·구제역 '3월 고비'…특별방역 1개월 연장",
            "excerpt": "■ AI 50건ㆍ야생조류 59건…위험지역 32곳 특별점검 = 이번 동절기('25/'26 시즌) 가금농장에서는 고병원성 조류인플루엔자가 50건, ...",
            "body": "네이버 뉴스 검색 결과입니다.<br><br>■ AI 50건ㆍ야생조류 59건…위험지역 32곳 특별점검 = 이번 동절기('25/'26 시즌) 가금농장에서는 고병원성 조류인플루엔자가 50건, 야생조류에서는 59건 발생했다. 지난 시즌보다 47일 빠르게 첫 발생했고, 검출 지역도... <br><br><a href='http://www.youngnong.co.kr/news/articleView.html?idxno=57859' target='_blank' style='color:#3a86ff; text-decoration:underline;'>원문 기사 보러가기</a>",
            "source": "네이버 뉴스",
            "image": "images/bird_flu.png",
            "daysAgo": 7,
            "date": "26.03.04",
            "link": "http://www.youngnong.co.kr/news/articleView.html?idxno=57859"
        },
        {
            "id": 27,
            "title": "AI 감염 위험 큰 '동물 살처분 인력' 98%가 외국인…방역 구멍 우려",
            "excerpt": "호남은 국내 최초로 야생 포유류인 삵에서 고병원성 AI가 검출된 지역이다. 조류에서만 확인되던 AI... <용어설명> ■ 조류인플루엔자(Avia...",
            "body": "네이버 뉴스 검색 결과입니다.<br><br>호남은 국내 최초로 야생 포유류인 삵에서 고병원성 AI가 검출된 지역이다. 조류에서만 확인되던 AI... <용어설명> ■ 조류인플루엔자(Avian Influenza, AI) 조류인플루엔자는 급성 바이러스성 전염병으로, 닭·오리 등... <br><br><a href='https://n.news.naver.com/mnews/article/421/0008809749?sid=105' target='_blank' style='color:#3a86ff; text-decoration:underline;'>원문 기사 보러가기</a>",
            "source": "네이버 뉴스",
            "image": "images/bird_flu.png",
            "daysAgo": 5,
            "date": "26.03.06",
            "link": "https://n.news.naver.com/mnews/article/421/0008809749?sid=105"
        },
        {
            "id": 28,
            "title": "감염력 10배 고병원성 조류인플루엔자 주의보",
            "excerpt": "또 N1타입은 천안, 아산 등 도내의 동쪽인 내륙, N9은 보령, 예산 등 도내 해안가에서 발생한 점으로 미뤄 조류인플루엔자 매개인 철새군의 이...",
            "body": "네이버 뉴스 검색 결과입니다.<br><br>또 N1타입은 천안, 아산 등 도내의 동쪽인 내륙, N9은 보령, 예산 등 도내 해안가에서 발생한 점으로 미뤄 조류인플루엔자 매개인 철새군의 이동 경로에 따라 전파한 것으로 추정된다고 덧붙였다. 가축위생방역지원본부... <br><br><a href='https://n.news.naver.com/mnews/article/656/0000169968?sid=102' target='_blank' style='color:#3a86ff; text-decoration:underline;'>원문 기사 보러가기</a>",
            "source": "네이버 뉴스",
            "image": "images/bird_flu.png",
            "daysAgo": 1,
            "date": "26.03.10",
            "link": "https://n.news.naver.com/mnews/article/656/0000169968?sid=102"
        },
        {
            "id": 29,
            "title": "김제 백산면 육용종계, 조류인플루엔자 H5형 항원 검출",
            "excerpt": "민선식 전북자치도 농생명축산산업국장은 \"조류인플루엔자 예방을 위해 축산종사자는 철새도래지 출입 금지와 농장 소독 등 기본 방역수칙을 철저히 준수...",
            "body": "네이버 뉴스 검색 결과입니다.<br><br>민선식 전북자치도 농생명축산산업국장은 \"조류인플루엔자 예방을 위해 축산종사자는 철새도래지 출입 금지와 농장 소독 등 기본 방역수칙을 철저히 준수하고, 3월 철새 북상 시기까지 긴장의 끈을 늦추지 말고... <br><br><a href='http://www.newskr.kr/news/articleView.html?idxno=103446' target='_blank' style='color:#3a86ff; text-decoration:underline;'>원문 기사 보러가기</a>",
            "source": "네이버 뉴스",
            "image": "images/bird_flu.png",
            "daysAgo": 1,
            "date": "26.03.10",
            "link": "http://www.newskr.kr/news/articleView.html?idxno=103446"
        },
        {
            "id": 30,
            "title": "김제 백산 육용종계 농가서 조류인플루엔자 H5형 항원 검출",
            "excerpt": "민선식 전북도 농생명축산산업국장은 \"조류인플루엔자 예방을 위해 축산종사자는 철새도래지 출입 금지와 농장 소독 등 기본 방역 수칙을 철저히 준수하...",
            "body": "네이버 뉴스 검색 결과입니다.<br><br>민선식 전북도 농생명축산산업국장은 \"조류인플루엔자 예방을 위해 축산종사자는 철새도래지 출입 금지와 농장 소독 등 기본 방역 수칙을 철저히 준수하고 3월 철새 북상 시기까지 긴장의 끈을 늦추지 말고 차단방역... <br><br><a href='https://n.news.naver.com/mnews/article/421/0008815829?sid=102' target='_blank' style='color:#3a86ff; text-decoration:underline;'>원문 기사 보러가기</a>",
            "source": "네이버 뉴스",
            "image": "images/bird_flu.png",
            "daysAgo": 2,
            "date": "26.03.09",
            "link": "https://n.news.naver.com/mnews/article/421/0008815829?sid=102"
        },
        {
            "id": 31,
            "title": "김제 백산면 육용종계, 고병원성 조류인플루엔자 H5N1 확진",
            "excerpt": "이재욱 전북자치도 동물방역과장은 \"조류인플루엔자 예방과 확산 방지를 위해 축산 관련 종사자는 철새도래지 출입을 금지하고, 농장 출입 차량 및 출...",
            "body": "네이버 뉴스 검색 결과입니다.<br><br>이재욱 전북자치도 동물방역과장은 \"조류인플루엔자 예방과 확산 방지를 위해 축산 관련 종사자는 철새도래지 출입을 금지하고, 농장 출입 차량 및 출입자 소독, 장화 교체, 매일 축사 내·외부 소독 등 방역수칙을... <br><br><a href='https://www.dailysportshankook.co.kr/news/articleView.html?idxno=425476' target='_blank' style='color:#3a86ff; text-decoration:underline;'>원문 기사 보러가기</a>",
            "source": "네이버 뉴스",
            "image": "images/bird_flu.png",
            "daysAgo": 0,
            "date": "26.03.11",
            "link": "https://www.dailysportshankook.co.kr/news/articleView.html?idxno=425476"
        }
    ],
    "ecosystem": [
        {
            "id": 32,
            "title": "'노랑알락하늘소' 생태계위해우려 생물 지정",
            "excerpt": "신석효 낙동강유역환경청장 직무대리는 “노랑알락하늘소가 생태계로 유출될 경우 남해안 일대 산림 생태계에 피해가 우려된다”며 “외래 생물에 의한 생...",
            "body": "네이버 뉴스 검색 결과입니다.<br><br>신석효 낙동강유역환경청장 직무대리는 “노랑알락하늘소가 생태계로 유출될 경우 남해안 일대 산림 생태계에 피해가 우려된다”며 “외래 생물에 의한 생태계 교란을 막기 위해 지역사회의 적극적인 관심과 협조를... <br><br><a href='https://n.news.naver.com/mnews/article/003/0013813525?sid=102' target='_blank' style='color:#3a86ff; text-decoration:underline;'>원문 기사 보러가기</a>",
            "source": "네이버 뉴스",
            "image": "images/env_gov.png",
            "daysAgo": 1,
            "date": "26.03.10",
            "link": "https://n.news.naver.com/mnews/article/003/0013813525?sid=102"
        },
        {
            "id": 33,
            "title": "청계천 생태계 위협 ‘외래 거북이’ 서울시, 사상 첫 포획작전 나선다",
            "excerpt": "이 중 패닌슐라쿠터(55마리)를 제외한 6종(278마리)은 모두 정부가 지정한 생태계 교란 생물이다. 반면 남생이, 자라 등 토착 거북 2종은 ...",
            "body": "네이버 뉴스 검색 결과입니다.<br><br>이 중 패닌슐라쿠터(55마리)를 제외한 6종(278마리)은 모두 정부가 지정한 생태계 교란 생물이다. 반면 남생이, 자라 등 토착 거북 2종은 159마리에 불과했다. 나머지 31마리는 거리가 멀어 종(種) 확인이 불가했다.... <br><br><a href='https://n.news.naver.com/mnews/article/016/0002611188?sid=102' target='_blank' style='color:#3a86ff; text-decoration:underline;'>원문 기사 보러가기</a>",
            "source": "네이버 뉴스",
            "image": "images/bullfrog.png",
            "daysAgo": 1,
            "date": "26.03.10",
            "link": "https://n.news.naver.com/mnews/article/016/0002611188?sid=102"
        },
        {
            "id": 34,
            "title": "안양시, 시민 참여형 생태계 교란식물 제거활동 참가자 모집",
            "excerpt": "시민과 단체가 참여하는 등 큰 호응을 얻은 바 있다. 시 관계자는 \"시민과 함께 생태계 교란식물을 제거해 하천 생태계의 건강성을 회복하고 생물다...",
            "body": "네이버 뉴스 검색 결과입니다.<br><br>시민과 단체가 참여하는 등 큰 호응을 얻은 바 있다. 시 관계자는 \"시민과 함께 생태계 교란식물을 제거해 하천 생태계의 건강성을 회복하고 생물다양성 보전에 기여할 수 있도록 많은 관심과 참여를 바란다\"고 밝혔다.<br><br><a href='https://www.gukjenews.com/news/articleView.html?idxno=3524319' target='_blank' style='color:#3a86ff; text-decoration:underline;'>원문 기사 보러가기</a>",
            "source": "네이버 뉴스",
            "image": "images/env_gov.png",
            "daysAgo": 2,
            "date": "26.03.09",
            "link": "https://www.gukjenews.com/news/articleView.html?idxno=3524319"
        },
        {
            "id": 35,
            "title": "안양시, 생태계 교란식물 제거 활동 참여자 모집",
            "excerpt": "시 관계자는 \"시민과 함께 생태계 교란식물을 제거해 하천 생태계의 건강성을 회복하고 생물다양성 보전에 기여할 수 있도록 많은 관심과 참여를 바란...",
            "body": "네이버 뉴스 검색 결과입니다.<br><br>시 관계자는 \"시민과 함께 생태계 교란식물을 제거해 하천 생태계의 건강성을 회복하고 생물다양성 보전에 기여할 수 있도록 많은 관심과 참여를 바란다\"고 말했다. [신아일보] 안양<br><br><a href='http://www.shinailbo.co.kr/news/articleView.html?idxno=2200188' target='_blank' style='color:#3a86ff; text-decoration:underline;'>원문 기사 보러가기</a>",
            "source": "네이버 뉴스",
            "image": "images/env_gov.png",
            "daysAgo": 1,
            "date": "26.03.10",
            "link": "http://www.shinailbo.co.kr/news/articleView.html?idxno=2200188"
        },
        {
            "id": 36,
            "title": "단양강 물속 조사해 보니…쏘가리보다 강준치·배스 더 많아",
            "excerpt": "또 외래생물이자 생태계 교란 어종인 배스와 최근 유해 야생생물로 지정된 민물가마우지로 인해 쏘가리 자원이 줄고 있어 관리가 필요하다고 진단했다....",
            "body": "네이버 뉴스 검색 결과입니다.<br><br>또 외래생물이자 생태계 교란 어종인 배스와 최근 유해 야생생물로 지정된 민물가마우지로 인해 쏘가리 자원이 줄고 있어 관리가 필요하다고 진단했다. 아울러 쏘가리뿐 아니라 꺽지, 끄리, 누치, 배스 등 단양강에... <br><br><a href='https://n.news.naver.com/mnews/article/001/0015950381?sid=102' target='_blank' style='color:#3a86ff; text-decoration:underline;'>원문 기사 보러가기</a>",
            "source": "네이버 뉴스",
            "image": "images/bullfrog.png",
            "daysAgo": 1,
            "date": "26.03.10",
            "link": "https://n.news.naver.com/mnews/article/001/0015950381?sid=102"
        },
        {
            "id": 37,
            "title": "외래 '유입주의 생물' 152종 사전 차단…자료집 배포",
            "excerpt": "국제적으로 생태계 위해성이 확인된 종이나, 사회적·생태적 피해 사례가 있는 종, 혹은 기존 생태계 교란 생물과 유전적·생태적 특성이 유사한 종 ...",
            "body": "네이버 뉴스 검색 결과입니다.<br><br>국제적으로 생태계 위해성이 확인된 종이나, 사회적·생태적 피해 사례가 있는 종, 혹은 기존 생태계 교란 생물과 유전적·생태적 특성이 유사한 종 등이 후보종에 포함된다. 기후부는 지난해 12월 30일 152종을 신규... <br><br><a href='https://n.news.naver.com/mnews/article/003/0013787127?sid=101' target='_blank' style='color:#3a86ff; text-decoration:underline;'>원문 기사 보러가기</a>",
            "source": "네이버 뉴스",
            "image": "images/env_gov.png",
            "daysAgo": 14,
            "date": "26.02.25",
            "link": "https://n.news.naver.com/mnews/article/003/0013787127?sid=101"
        },
        {
            "id": 38,
            "title": "국립생태원, '유입주의 생물 152종 자료집 Ⅶ' 발간",
            "excerpt": "김경석 기후에너지환경부 생물다양성과장은 \"유입주의 생물 지정·관리는 생태계 교란을 사전에 차단하는 핵심 수단\"이라며, \"앞으로도 외래생물 관리를...",
            "body": "네이버 뉴스 검색 결과입니다.<br><br>김경석 기후에너지환경부 생물다양성과장은 \"유입주의 생물 지정·관리는 생태계 교란을 사전에 차단하는 핵심 수단\"이라며, \"앞으로도 외래생물 관리를 강화해 나갈 것\"이라고 말했다. '유입주의 생물 152종 자료집... <br><br><a href='http://www.ikld.kr/news/articleView.html?idxno=330040' target='_blank' style='color:#3a86ff; text-decoration:underline;'>원문 기사 보러가기</a>",
            "source": "네이버 뉴스",
            "image": "images/env_gov.png",
            "daysAgo": 13,
            "date": "26.02.26",
            "link": "http://www.ikld.kr/news/articleView.html?idxno=330040"
        },
        {
            "id": 39,
            "title": "\"화려함 앞세운 새벼리 야간조명..빛공해·생태 교란 우려 확산\"",
            "excerpt": "\"화려함 앞세운 새벼리 야간조명..빛공해·생태 교란 우려 확산\"\"화려함 앞세운 새벼리 야간조명..빛공해... 등 생태계 전반에 영향을 미친다는 ...",
            "body": "네이버 뉴스 검색 결과입니다.<br><br>\"화려함 앞세운 새벼리 야간조명..빛공해·생태 교란 우려 확산\"\"화려함 앞세운 새벼리 야간조명..빛공해... 등 생태계 전반에 영향을 미친다는 결과가 잇따르고 있다. 남강 변 절벽과 수변 공간은 다양한 생물의 이동... <br><br><a href='http://www.dandinews.com/news/articleView.html?idxno=16474' target='_blank' style='color:#3a86ff; text-decoration:underline;'>원문 기사 보러가기</a>",
            "source": "네이버 뉴스",
            "image": "images/env_gov.png",
            "daysAgo": 8,
            "date": "26.03.03",
            "link": "http://www.dandinews.com/news/articleView.html?idxno=16474"
        },
        {
            "id": 40,
            "title": "충주시, 야생생물 1마리라도 사육할 경우 반드시 지자체 신고 의무화",
            "excerpt": "충주시청 충주시가 개정된 「야생생물 보호 및 관리에 관한 법률」에 따라 야생생물을 1마리라도 사육할... 국내 생태계 교란을 방지할 계획이다. ...",
            "body": "네이버 뉴스 검색 결과입니다.<br><br>충주시청 충주시가 개정된 「야생생물 보호 및 관리에 관한 법률」에 따라 야생생물을 1마리라도 사육할... 국내 생태계 교란을 방지할 계획이다. 그동안 관리 사각지대에 있던 야생동물을 제도권 내로 편입해... <br><br><a href='http://www.newstown.co.kr/news/articleView.html?idxno=694428' target='_blank' style='color:#3a86ff; text-decoration:underline;'>원문 기사 보러가기</a>",
            "source": "네이버 뉴스",
            "image": "images/env_gov.png",
            "daysAgo": 20,
            "date": "26.02.19",
            "link": "http://www.newstown.co.kr/news/articleView.html?idxno=694428"
        },
        {
            "id": 41,
            "title": "서울 생물의 절반 이상 ‘생태경관보전지역’에 서식",
            "excerpt": "종의 생물이 서식하는 것으로 확인됐다. 서울연구원은 최근 ‘서울시 생태·경관보전지역 동식물상 변화... 이외에도 이번 조사에서 보전지역에 생태계...",
            "body": "네이버 뉴스 검색 결과입니다.<br><br>종의 생물이 서식하는 것으로 확인됐다. 서울연구원은 최근 ‘서울시 생태·경관보전지역 동식물상 변화... 이외에도 이번 조사에서 보전지역에 생태계교란종 미국쑥부쟁이, 서양등골나무, 환삼덩굴, 돼지풀 등의... <br><br><a href='http://www.lak.co.kr/news/boardview.php?id=22574' target='_blank' style='color:#3a86ff; text-decoration:underline;'>원문 기사 보러가기</a>",
            "source": "네이버 뉴스",
            "image": "images/env_gov.png",
            "daysAgo": 12,
            "date": "26.02.27",
            "link": "http://www.lak.co.kr/news/boardview.php?id=22574"
        }
    ],
    "association": [
        {
            "id": 42,
            "title": "영산강청, 장성 일대서 야생동물 불법 엽구 27점 수거",
            "excerpt": "영산강청에 따르면 장성군과 내장산 국립공원 백암사무소, 야생생물관리협회 광주전남지부 등 유관기관이 함께한 이번 수거는 겨울철 먹이 부족으로 민가...",
            "body": "네이버 뉴스 검색 결과입니다.<br><br>영산강청에 따르면 장성군과 내장산 국립공원 백암사무소, 야생생물관리협회 광주전남지부 등 유관기관이 함께한 이번 수거는 겨울철 먹이 부족으로 민가 인근까지 내려오는 야생동물을 노린 불법 포획 행위를 근절하기... <br><br><a href='https://n.news.naver.com/mnews/article/421/0008793478?sid=102' target='_blank' style='color:#3a86ff; text-decoration:underline;'>원문 기사 보러가기</a>",
            "source": "네이버 뉴스",
            "image": "images/env_gov.png",
            "daysAgo": 14,
            "date": "26.02.25",
            "link": "https://n.news.naver.com/mnews/article/421/0008793478?sid=102"
        },
        {
            "id": 43,
            "title": "야생생물관리협회 예천지회, 예천군에 고향사랑기부금 기탁",
            "excerpt": "야생생물관리협회 예천지회(회장 김정규)가 26일 예천군청을 방문, 고향사랑기부금 300만 원을 김학동 군수를 통해 지정 기탁했다. 김학동 군수는...",
            "body": "네이버 뉴스 검색 결과입니다.<br><br>야생생물관리협회 예천지회(회장 김정규)가 26일 예천군청을 방문, 고향사랑기부금 300만 원을 김학동 군수를 통해 지정 기탁했다. 김학동 군수는 \"야생생물관리협회 예천지회 회원과 가족분들의 따뜻한 관심과 지원에... <br><br><a href='https://www.dkilbo.com/news/articleView.html?idxno=535107' target='_blank' style='color:#3a86ff; text-decoration:underline;'>원문 기사 보러가기</a>",
            "source": "네이버 뉴스",
            "image": "images/env_gov.png",
            "daysAgo": 13,
            "date": "26.02.26",
            "link": "https://www.dkilbo.com/news/articleView.html?idxno=535107"
        },
        {
            "id": 44,
            "title": "[현장속으로]열 걸음마다 철제 올무...죽음 위기 내몰린 야생동물들",
            "excerpt": "야생생물관리협회 관계자는 \"이런 매듭은 몸이 잘리지 않는 한 동물이 스스로 풀 수 없다\"며 \"전국이 올무로 뒤덮였다고 해도 과언이 아닐 정도\"라...",
            "body": "네이버 뉴스 검색 결과입니다.<br><br>야생생물관리협회 관계자는 \"이런 매듭은 몸이 잘리지 않는 한 동물이 스스로 풀 수 없다\"며 \"전국이 올무로 뒤덮였다고 해도 과언이 아닐 정도\"라고 말했다. 이날 영산강유역환경청은 장성군 내 한 야산에서 불법 엽구... <br><br><a href='https://www.namdonews.com/news/articleView.html?idxno=902438' target='_blank' style='color:#3a86ff; text-decoration:underline;'>원문 기사 보러가기</a>",
            "source": "네이버 뉴스",
            "image": "images/env_gov.png",
            "daysAgo": 14,
            "date": "26.02.25",
            "link": "https://www.namdonews.com/news/articleView.html?idxno=902438"
        },
        {
            "id": 45,
            "title": "북구, 야생동물 밀렵·밀거래 단속",
            "excerpt": "북구는 2025-2026 겨울철 야생동물 밀렵·밀거래 특별단속 기간에 따라 야생생물관리협회 울산지회, 북구 유해야생동물 피해방지단과 함께 합동 ...",
            "body": "네이버 뉴스 검색 결과입니다.<br><br>북구는 2025-2026 겨울철 야생동물 밀렵·밀거래 특별단속 기간에 따라 야생생물관리협회 울산지회, 북구 유해야생동물 피해방지단과 함께 합동 단속을 벌여 불법 포획에 대한 경각심을 높이고 야생동물 피해 및 시민... <br><br><a href='http://www.ujeil.com/news/articleView.html?idxno=381473' target='_blank' style='color:#3a86ff; text-decoration:underline;'>원문 기사 보러가기</a>",
            "source": "네이버 뉴스",
            "image": "images/police.png",
            "daysAgo": 17,
            "date": "26.02.22",
            "link": "http://www.ujeil.com/news/articleView.html?idxno=381473"
        },
        {
            "id": 46,
            "title": "울산 북구, 야생동물 밀렵·밀거래 합동 단속 및 불법 도구 수거",
            "excerpt": "북구는 2025-2026 겨울철 야생동물 밀렵·밀거래 특별단속 기간에 따라 이날 야생생물관리협회 울산지회, 북구 유해야생동물 피해방지단과 함께 ...",
            "body": "네이버 뉴스 검색 결과입니다.<br><br>북구는 2025-2026 겨울철 야생동물 밀렵·밀거래 특별단속 기간에 따라 이날 야생생물관리협회 울산지회, 북구 유해야생동물 피해방지단과 함께 합동 단속을 벌여 불법 포획에 대한 경각심을 높이고 야생동물 피해 및 시민... <br><br><a href='https://www.ksilbo.co.kr/news/articleView.html?idxno=1049588' target='_blank' style='color:#3a86ff; text-decoration:underline;'>원문 기사 보러가기</a>",
            "source": "네이버 뉴스",
            "image": "images/police.png",
            "daysAgo": 18,
            "date": "26.02.21",
            "link": "https://www.ksilbo.co.kr/news/articleView.html?idxno=1049588"
        },
        {
            "id": 47,
            "title": "야생생물관리협회 부산·울산·경남지부 합천지회 하세철 신임회장 취임",
            "excerpt": "▲ /합천군 야생생물관리협회 부산·울산·경남지부 합천지회는 5일 합천군청 제2청사 3층 회의실에서 회원 30여 명이 참석한 가운데 2026년 정...",
            "body": "네이버 뉴스 검색 결과입니다.<br><br>▲ /합천군 야생생물관리협회 부산·울산·경남지부 합천지회는 5일 합천군청 제2청사 3층 회의실에서 회원 30여 명이 참석한 가운데 2026년 정기총회와 회장 이·취임식을 개최했다. 이날 정기총회에서는 2025년도 협회... <br><br><a href='http://www.gndomin.com/news/articleView.html?idxno=464580' target='_blank' style='color:#3a86ff; text-decoration:underline;'>원문 기사 보러가기</a>",
            "source": "네이버 뉴스",
            "image": "images/env_gov.png",
            "daysAgo": 31,
            "date": "26.02.08",
            "link": "http://www.gndomin.com/news/articleView.html?idxno=464580"
        },
        {
            "id": 48,
            "title": "여수서 야생 동물 해체하던 60대 등 2명 붙잡혀",
            "excerpt": "유해조수 출몰·피해 시 행정기관의 의뢰를 받고 포획 활동을 펼쳐온 것으로 알려졌다. 경찰은 A씨 등이 야생생물관리협회 회원 자격 여부와 여수시 ...",
            "body": "네이버 뉴스 검색 결과입니다.<br><br>유해조수 출몰·피해 시 행정기관의 의뢰를 받고 포획 활동을 펼쳐온 것으로 알려졌다. 경찰은 A씨 등이 야생생물관리협회 회원 자격 여부와 여수시 유해조수구제 의뢰·총기 반출 등에 대해 조사 중에 있다. 동부취재본부<br><br><a href='https://www.namdonews.com/news/articleView.html?idxno=900731' target='_blank' style='color:#3a86ff; text-decoration:underline;'>원문 기사 보러가기</a>",
            "source": "네이버 뉴스",
            "image": "images/police.png",
            "daysAgo": 31,
            "date": "26.02.08",
            "link": "https://www.namdonews.com/news/articleView.html?idxno=900731"
        },
        {
            "id": 49,
            "title": "야생생물관리협회 부산·울산·경남지부 합천지회, 제10회 정기총회 및...",
            "excerpt": "야생생물관리협회 부산·울산·경남지부 합천지회는 5일 합천군청 제2청사 3층 회의실에서 회원 30여 명이 참석한 가운데 2026년 정기총회와 회장...",
            "body": "네이버 뉴스 검색 결과입니다.<br><br>야생생물관리협회 부산·울산·경남지부 합천지회는 5일 합천군청 제2청사 3층 회의실에서 회원 30여 명이 참석한 가운데 2026년 정기총회와 회장 이·취임식을 개최했다. 이날 정기총회에서는 2025년도 협회 운영과 주요... <br><br><a href='https://www.siminilbo.co.kr/news/newsview.php?ncode=1160291309387257' target='_blank' style='color:#3a86ff; text-decoration:underline;'>원문 기사 보러가기</a>",
            "source": "네이버 뉴스",
            "image": "images/env_gov.png",
            "daysAgo": 33,
            "date": "26.02.06",
            "link": "https://www.siminilbo.co.kr/news/newsview.php?ncode=1160291309387257"
        },
        {
            "id": 50,
            "title": "김천시, 야생생물관리협회와 로드킬 처리 상시기동반 운영 '맞손'",
            "excerpt": "▲김천시와 야생생물관리협회 김천지회는 지난 8일 로드킬 동물사체 처리 상시기동반 운영을 위해 업무 협약을 체결했다. 김천시 제공 김천시와 야생생...",
            "body": "네이버 뉴스 검색 결과입니다.<br><br>▲김천시와 야생생물관리협회 김천지회는 지난 8일 로드킬 동물사체 처리 상시기동반 운영을 위해 업무 협약을 체결했다. 김천시 제공 김천시와 야생생물관리협회 김천지회는 지난 8일 로드킬 동물사체 처리... <br><br><a href='https://www.dkilbo.com/news/articleView.html?idxno=529668' target='_blank' style='color:#3a86ff; text-decoration:underline;'>원문 기사 보러가기</a>",
            "source": "네이버 뉴스",
            "image": "images/env_gov.png",
            "daysAgo": 59,
            "date": "26.01.11",
            "link": "https://www.dkilbo.com/news/articleView.html?idxno=529668"
        },
        {
            "id": 51,
            "title": "김천시, 야생생물관리협회와 로드킬 처리 업무협약",
            "excerpt": "김천시, 야생생물관리협회와 로드킬 처리 업무협약 김천시는 지난 8일 '로드킬 동물사체 처리 상시기동반'운영을 위해 야생생물관리협회 김천지회와 로...",
            "body": "네이버 뉴스 검색 결과입니다.<br><br>김천시, 야생생물관리협회와 로드킬 처리 업무협약 김천시는 지난 8일 '로드킬 동물사체 처리 상시기동반'운영을 위해 야생생물관리협회 김천지회와 로드킬 처리 업무협약을 체결했다. 상시기동반은 밤낮을 가리지... <br><br><a href='https://www.thebk.co.kr/news/articleView.html?idxno=306181' target='_blank' style='color:#3a86ff; text-decoration:underline;'>원문 기사 보러가기</a>",
            "source": "네이버 뉴스",
            "image": "images/env_gov.png",
            "daysAgo": 61,
            "date": "26.01.09",
            "link": "https://www.thebk.co.kr/news/articleView.html?idxno=306181"
        }
    ],
    "editorial": [
        {
            "id": 1,
            "title": "[사설] 실탄관리 법개정, 국회에서 총기까지 확대해야",
            "excerpt": "‘사격 및 사격장 안전관리에 관한 법률’을 개정해 사격장 실탄 관리 절차를 구체화하고, 형사처벌과... 인명 살상이 가능한 실탄 관리는 전무했고...",
            "body": "네이버 뉴스 검색 결과입니다.<br><br>‘사격 및 사격장 안전관리에 관한 법률’을 개정해 사격장 실탄 관리 절차를 구체화하고, 형사처벌과... 인명 살상이 가능한 실탄 관리는 전무했고 불법총기 단속은 무력했다. 수렵 현장에서는 오래된 불법이라는 증언이... <br><br><a href='https://www.kyeongin.com/article/1758616' target='_blank' style='color:#3a86ff; text-decoration:underline;'>원문 기사 보러가기</a>",
            "source": "네이버 뉴스",
            "image": "images/police.png",
            "daysAgo": 36,
            "date": "26.02.03",
            "link": "https://www.kyeongin.com/article/1758616"
        },
        {
            "id": 11,
            "title": "[우분투칼럼] 안창호의 빗자루질…'아프리카돼지열병' 낙인을 쓸자",
            "excerpt": "사용하는 '아프리카돼지열병'(African Swine Fever·ASF)이라는 용어다. 이 질병은 1921년 동아프리카 케냐에서 처음... 이미...",
            "body": "네이버 뉴스 검색 결과입니다.<br><br>사용하는 '아프리카돼지열병'(African Swine Fever·ASF)이라는 용어다. 이 질병은 1921년 동아프리카 케냐에서 처음... 이미 바이러스는 유럽과 아시아의 야생 멧돼지 사이에서 토착화돼 아프리카와는 무관하게 생존하고 있다.... <br><br><a href='https://n.news.naver.com/mnews/article/001/0015948695?sid=101' target='_blank' style='color:#3a86ff; text-decoration:underline;'>원문 기사 보러가기</a>",
            "source": "네이버 뉴스",
            "image": "images/boar.png",
            "daysAgo": 1,
            "date": "26.03.10",
            "link": "https://n.news.naver.com/mnews/article/001/0015948695?sid=101"
        },
        {
            "id": 52,
            "title": "[사설] 사람과 자연 공존하는 금정산 관리 계획을",
            "excerpt": "금정산은 수많은 희귀 야생동물이 자라고 각종 문화유산과 경관을 가져 최고의 국립공원이 될 수 있는 자원을 충분히 갖추고 있다. 외국인 관광객 연...",
            "body": "네이버 뉴스 검색 결과입니다.<br><br>금정산은 수많은 희귀 야생동물이 자라고 각종 문화유산과 경관을 가져 최고의 국립공원이 될 수 있는 자원을 충분히 갖추고 있다. 외국인 관광객 연간 500만 명 유치를 목표로 하는 부산은 바다 강 산을 연결하는... <br><br><a href='https://n.news.naver.com/mnews/article/658/0000136805?sid=110' target='_blank' style='color:#3a86ff; text-decoration:underline;'>원문 기사 보러가기</a>",
            "source": "네이버 뉴스",
            "image": "images/env_gov.png",
            "daysAgo": 8,
            "date": "26.03.03",
            "link": "https://n.news.naver.com/mnews/article/658/0000136805?sid=110"
        },
        {
            "id": 53,
            "title": "[사설] 진주시 진양호동물원 수의사 찾기 대책을",
            "excerpt": "그러나 3년 전부터 전담 수의사 채용 공고를 냈지만, 공영 동물원이다 보니 전담 수의사 임금을 사설 동물원... 또한 급여 외에, 야생동물 보전...",
            "body": "네이버 뉴스 검색 결과입니다.<br><br>그러나 3년 전부터 전담 수의사 채용 공고를 냈지만, 공영 동물원이다 보니 전담 수의사 임금을 사설 동물원... 또한 급여 외에, 야생동물 보전과 복지 연구라는 특수한 경험, 논문 출판 및 국외 동물원과 교류 기회 등을... <br><br><a href='https://www.idomin.com/news/articleView.html?idxno=2000382' target='_blank' style='color:#3a86ff; text-decoration:underline;'>원문 기사 보러가기</a>",
            "source": "네이버 뉴스",
            "image": "images/env_gov.png",
            "daysAgo": 7,
            "date": "26.03.04",
            "link": "https://www.idomin.com/news/articleView.html?idxno=2000382"
        },
        {
            "id": 54,
            "title": "[사설] 아프리카돼지열병, 정확한 원인 규명이 우선",
            "excerpt": "야생동물 관리, 사람 이동, 사료 원료 수입·가공 공정 등 모든 단계에 대한 데이터 기반 추적이 동시에 이뤄져야 한다. 또한 조사 과정과 근거를...",
            "body": "네이버 뉴스 검색 결과입니다.<br><br>야생동물 관리, 사람 이동, 사료 원료 수입·가공 공정 등 모든 단계에 대한 데이터 기반 추적이 동시에 이뤄져야 한다. 또한 조사 과정과 근거를 투명하게 공개해 정책 신뢰를 회복해야 한다. 오락가락·우왕좌왕하는... <br><br><a href='https://n.news.naver.com/mnews/article/662/0000089463?sid=110' target='_blank' style='color:#3a86ff; text-decoration:underline;'>원문 기사 보러가기</a>",
            "source": "네이버 뉴스",
            "image": "images/boar.png",
            "daysAgo": 12,
            "date": "26.02.27",
            "link": "https://n.news.naver.com/mnews/article/662/0000089463?sid=110"
        },
        {
            "id": 55,
            "title": "[사설]울산 조류 충돌 방지, 공공시설 전면 의무화부터",
            "excerpt": "지난해 울산야생동물구조관리센터에 접수된 유리창·건물 충돌 구조 개체만 298마리다. 이는 신고와 발견을 전제로 한 수치다. 현장에서 즉사하거나 ...",
            "body": "네이버 뉴스 검색 결과입니다.<br><br>지난해 울산야생동물구조관리센터에 접수된 유리창·건물 충돌 구조 개체만 298마리다. 이는 신고와 발견을 전제로 한 수치다. 현장에서 즉사하거나 포식자에 의해 사라진 개체까지 감안하면 실제 피해는 더 클 가능성을... <br><br><a href='https://www.ksilbo.co.kr/news/articleView.html?idxno=1049382' target='_blank' style='color:#3a86ff; text-decoration:underline;'>원문 기사 보러가기</a>",
            "source": "네이버 뉴스",
            "image": "images/env_gov.png",
            "daysAgo": 20,
            "date": "26.02.19",
            "link": "https://www.ksilbo.co.kr/news/articleView.html?idxno=1049382"
        },
        {
            "id": 56,
            "title": "[사설]한중 우호교류의 상징 판다 한 쌍 우치동물원 올 것",
            "excerpt": "거점 동물원은 야생동물 보호와 동물 치료 등을 위해 지원금을 받는다. 광주시는 중국측으로부터 판다 대여가 확정되면 준비 기간이 2년 정도 소요될...",
            "body": "네이버 뉴스 검색 결과입니다.<br><br>거점 동물원은 야생동물 보호와 동물 치료 등을 위해 지원금을 받는다. 광주시는 중국측으로부터 판다 대여가 확정되면 준비 기간이 2년 정도 소요될 것으로 예상하고 정부와 긴밀히 소통하며 종합 검토하고 있다. 판다... <br><br><a href='http://www.kjdaily.com/article.php?aid=1767868906671091018' target='_blank' style='color:#3a86ff; text-decoration:underline;'>원문 기사 보러가기</a>",
            "source": "네이버 뉴스",
            "image": "images/env_gov.png",
            "daysAgo": 62,
            "date": "26.01.08",
            "link": "http://www.kjdaily.com/article.php?aid=1767868906671091018"
        },
        {
            "id": 57,
            "title": "[사설] 멧돼지 잇단 주택가 출몰 시민안전 이상 없나",
            "excerpt": "사설 [충청투데이 김승한 기자] 대전 도심지역 주택가에 멧돼지가 연이어 출몰하고 있어 시민들의 각별한... 어제 오전 9시 께 서구 도안동 근린...",
            "body": "네이버 뉴스 검색 결과입니다.<br><br>사설 [충청투데이 김승한 기자] 대전 도심지역 주택가에 멧돼지가 연이어 출몰하고 있어 시민들의 각별한... 어제 오전 9시 께 서구 도안동 근린공원에 멧돼지가 출몰했다는 신고가 들어와 서구청 유해야생동물... <br><br><a href='https://www.cctoday.co.kr/news/articleView.html?idxno=2224531' target='_blank' style='color:#3a86ff; text-decoration:underline;'>원문 기사 보러가기</a>",
            "source": "네이버 뉴스",
            "image": "images/boar.png",
            "daysAgo": 50,
            "date": "26.01.20",
            "link": "https://www.cctoday.co.kr/news/articleView.html?idxno=2224531"
        },
        {
            "id": 58,
            "title": "[사설] 원천호수 발견 고병원성 AI, 즉각 대처한 수원시",
            "excerpt": "수원특례시가 즉각 국립야생동물질병관리원에 검사를 의뢰한 결과 'H5형 항원'이 검출됐고 최종 검사에서 고병원성 AI 판정을 받은 것이다. 이에 ...",
            "body": "네이버 뉴스 검색 결과입니다.<br><br>수원특례시가 즉각 국립야생동물질병관리원에 검사를 의뢰한 결과 'H5형 항원'이 검출됐고 최종 검사에서 고병원성 AI 판정을 받은 것이다. 이에 수원시는 검출 지역 주변을 방역했고 산책로 부근에는 소독발판을... <br><br><a href='http://www.suwonilbo.kr/news/articleView.html?idxno=314129' target='_blank' style='color:#3a86ff; text-decoration:underline;'>원문 기사 보러가기</a>",
            "source": "네이버 뉴스",
            "image": "images/bird_flu.png",
            "daysAgo": 47,
            "date": "26.01.23",
            "link": "http://www.suwonilbo.kr/news/articleView.html?idxno=314129"
        },
        {
            "id": 59,
            "title": "[사설]ASF·AI 동시 확산, 방역에 빈틈 생겨선 안 돼",
            "excerpt": "철새의 이동 경로, 야생동물의 서식 환경, 축산 농가의 방역 취약지대를 고려한 중장기적 차원의 방역 전략이 시급하다. 특히 철새도래지 인근 농가...",
            "body": "네이버 뉴스 검색 결과입니다.<br><br>철새의 이동 경로, 야생동물의 서식 환경, 축산 농가의 방역 취약지대를 고려한 중장기적 차원의 방역 전략이 시급하다. 특히 철새도래지 인근 농가에 대해서는 사육 형태, 방역시설, 출입 통제 수준 등을 전수조사하고... <br><br><a href='https://n.news.naver.com/mnews/article/087/0001169297?sid=110' target='_blank' style='color:#3a86ff; text-decoration:underline;'>원문 기사 보러가기</a>",
            "source": "네이버 뉴스",
            "image": "images/bird_flu.png",
            "daysAgo": 48,
            "date": "26.01.22",
            "link": "https://n.news.naver.com/mnews/article/087/0001169297?sid=110"
        }
    ]
}